dotbins/__init__.py
dotbins/cli.py
dotbins/config.py
dotbins/detect_asset.py
dotbins/detect_binary.py
dotbins/download.py
dotbins/manifest.py
dotbins/py.typed
dotbins/readme.py
dotbins/summary.py
dotbins/utils.py
dotbins-2.6.0.dist-info/licenses/LICENSE
dotbins-2.6.0.dist-info/METADATA
dotbins-2.6.0.dist-info/WHEEL
dotbins-2.6.0.dist-info/entry_points.txt
dotbins-2.6.0.dist-info/top_level.txt
dotbins-2.6.0.dist-info/RECORD
