Metadata-Version: 2.4
Name: dotbins
Version: 2.6.0
Summary: Keep updated binaries in your dotfiles
Author-email: Bas Nijholt <bas@nijho.lt>
Project-URL: Homepage, https://github.com/basnijholt/dotbins
Requires-Python: >=3.9
License-File: LICENSE
Requires-Dist: requests
Requires-Dist: pyyaml
Requires-Dist: rich>=13.9.4
Requires-Dist: rich-argparse
Requires-Dist: typing-extensions>=4.11.0; python_version < "3.11"
Dynamic: license-file
